micpy/__init__.py
micpy/core.py
micpy/micpy.py
micpy/parameters.py
micpy-0.0.1.dist-info/LICENSE
micpy-0.0.1.dist-info/METADATA
micpy-0.0.1.dist-info/WHEEL
micpy-0.0.1.dist-info/top_level.txt
micpy-0.0.1.dist-info/RECORD
